uke/__init__.py
uke/__main__.py
uke/chord.py
uke/cli.py
uke/strum.py
uke/tmpl/__init__.py
uke/tmpl/base.jinja2
uke/tmpl/chord.jinja2
uke/tuner.py
uke-0.1.0.dev1.dist-info/entry_points.txt
uke-0.1.0.dev1.dist-info/LICENSE
uke-0.1.0.dev1.dist-info/METADATA
uke-0.1.0.dev1.dist-info/WHEEL
uke-0.1.0.dev1.dist-info/RECORD
